status/__init__.py
status/__main__.py
status/application.py
status/bootstrap.py
status/parser.py
status/py.typed
gros_status-1.0.0.dist-info/LICENSE
gros_status-1.0.0.dist-info/METADATA
gros_status-1.0.0.dist-info/WHEEL
gros_status-1.0.0.dist-info/entry_points.txt
gros_status-1.0.0.dist-info/top_level.txt
gros_status-1.0.0.dist-info/RECORD
