Metadata-Version: 2.1
Name: gros-status
Version: 1.0.0
Summary: Grip on Software status dashboard
Author-email: Leon Helwerda <l.s.helwerda@liacs.leidenuniv.nl>
License: Apache 2.0
Project-URL: Homepage, https://gros.liacs.nl
Project-URL: PyPI, https://pypi.python.org/pypi/gros-status
Project-URL: Source Code, https://github.com/grip-on-software/status-dashboard
Project-URL: Issues, https://github.com/grip-on-software/status-dashboard/issues
Project-URL: Pull Requests, https://github.com/grip-on-software/status-dashboard/pulls
Project-URL: CI: GitHub Actions, https://github.com/grip-on-software/status-dashboard/actions
Project-URL: CI: Coveralls, https://coveralls.io/github/grip-on-software/status-dashboard?branch=master
Project-URL: CI: SonarCloud, https://sonarcloud.io/project/overview?id=grip-on-software_status-dashboard
Keywords: status dashboard,agent-based,log parser
Classifier: Development Status :: 5 - Production/Stable
Classifier: Environment :: Web Environment
Classifier: Intended Audience :: Developers
Classifier: Topic :: Internet :: WWW/HTTP :: HTTP Servers
Classifier: License :: OSI Approved :: Apache Software License
Classifier: Operating System :: OS Independent
Classifier: Programming Language :: Python :: 3
Classifier: Programming Language :: Python :: 3.8
Classifier: Programming Language :: Python :: 3.9
Classifier: Programming Language :: Python :: 3.10
Classifier: Programming Language :: Python :: 3.11
Classifier: Programming Language :: Python :: 3.12
Requires-Python: >=3.8
License-File: LICENSE
Requires-Dist: gros-gatherer ==1.0.0
Requires-Dist: gros-server ==1.0.0
Requires-Dist: Pyro4 ==4.82
